{
  "content_overview": {
    "theme": "新手爸妈必看：宝宝夜醒频繁怎么办",
    "total_images": 4,
    "target_audience": "新手爸妈，特别是0-1岁宝宝家庭",
    "content_style": "图文并茂的“保姆级教程”，结合真实、接地气的个人经验分享",
    "persona_voice": "“暖男型理工爸”，理性、有条理，同时充满同理心和温柔"
  },
  "xiaohongshu_titles": [
    "保姆级攻略！宝宝夜醒排查指南快收藏",
    "手把手教你分析宝宝夜醒，3步就搞定",
    "亲测有效！用这招我家娃终于睡整觉了",
    "宝宝夜醒的4大元凶，这次给你讲透了",
    "别再瞎哄了！夜醒频繁的真相都在这",
    "讲真，搞懂这个比啥安抚神器都管用",
    "@新手爸妈 娃一晚醒8次我太懂你了！",
    "电量剩1%的爸妈，这份指南请收好",
    "这篇给所有被夜醒折磨的家庭",
    "告别熊猫眼，奶爸版睡眠攻略请查收",
    "抄作业！让宝宝安睡整晚的实操手册",
    "用这个方法，我和队友都解放了",
    "吐血整理！宝宝夜醒原因自查清单",
    "错过亏大！这份夜醒分析攻略必看",
    "年度干货！专治各种不睡觉的小魔头"
  ],
  "xiaohongshu_content": "“电量仅剩1%，全靠一口仙气吊着…”\n如果这也是你和队友每晚的真实写照，快停下那些无效的摇晃和安抚！\n\n我是宝爸Conn，一个娃刚满1岁的理工男奶爸。我把那段跟小宝“斗智斗勇”的熬鹰经历，总结成了一份《宝宝夜醒排查指南》，从“哄睡困难户”变身“睡眠分析师”，希望能帮到同样焦虑的你们。\n\n咱们家小宝3个月大的时候，有两周时间简直是小夜魔，一晚上能醒七八次，我和宝妈轮流抱，身心俱疲。后来我琢磨着，不能这么瞎哄，得像解bug一样找到根源。我做了个简单的排查表，结果你猜怎么着？连着3天，记录下来发现他每次醒都不是饿，而是因为后半夜房间温度降下来，他蹬了被子感觉冷了！就这么个小细节，折腾了我们两周！\n\n所以，别急着自我怀疑，也别急着给娃贴“睡渣”标签。育儿路上，咱们都是摸着石头过河的新手。这份指南，把复杂的睡眠问题拆解成简单的步骤，希望能让你和你的“神队友”找回并肩作战的感觉。\n\n@你的神队友 一起看看，评论区聊聊，你家娃属于哪种“夜醒困难户”？\n\n#宝宝夜醒 #新手爸妈 #科学育儿 #哄睡 #宝爸带娃 #育儿经验 #睡眠引导 #夫妻育儿 #整觉宝宝",
  "image_contents": [
    {
      "image_number": 1,
      "type": "封面图",
      "title": "宝宝频繁夜醒，真凶原来是…",
      "main_content": "主标题：【宝宝频繁夜醒，真凶原来是…】\n副标题：奶爸版睡眠侦探指南 | 3步搞定夜醒难题\n点缀文案：亲身经历，告别无效安抚！",
      "visual_elements": [
        "醒目大标题",
        "副标题",
        "“亲身经历”标签",
        "温暖的婴儿房插画背景"
      ],
      "color_scheme": "温暖橙色系，如#FFF4E6背景搭配深棕色#4E342E文字",
      "layout": "顶部大标题，中部副标题，底部点缀元素，整体视觉居中",
      "height_constraint": "严格控制在560px以内"
    },
    {
      "image_number": 2,
      "type": "内容图",
      "title": "第一步：先当5分钟“睡眠侦探”",
      "main_content": "标题：① 先观察，后行动！\n核心内容：制作一个“宝宝夜醒原因自查表”，用简单的图标+文字，列出四大排查方向：\n1.【生理需求】：饿了？渴了？尿布湿了？（图标：奶瓶+尿布）\n2.【环境因素】：冷了？热了？光太亮？有噪音？（图标：温度计+太阳）\n3.【白天因素】：活动量够吗？小睡是否合理？（图标：玩具+时钟）\n4.【睡眠联想】：是不是必须奶睡或抱睡才能接觉？（图标：手臂+月亮）\n个人分享模块：“我家就踩过坑，总以为是饿，结果发现是房间太热，娃踢了被子。做个简单记录，比瞎猜管用多了！”",
      "visual_elements": [
        "清单式列表",
        "图标辅助说明",
        "“我的踩坑经历”对话框模块",
        "步骤编号'①'"
      ],
      "color_scheme": "清新绿色系，如#E8F5E9背景搭配深绿色#2E7D32标题",
      "layout": "顶部标题，主体为四宫格清单布局，底部穿插个人分享的对话框",
      "height_constraint": "严格控制在560px以内"
    },
    {
      "image_number": 3,
      "type": "内容图",
      "title": "第二步：激活你的“神队友”",
      "main_content": "标题：② 夫妻是战友，不是孤军奋战！\n核心内容：展示一张设计好的《夫妻夜间轮值表示例》，包含列：\n- 【时间段】：如 23:00-02:00 / 02:00-05:00\n- 【主负责人】：爸爸 / 妈妈\n- 【任务清单】：喂奶 / 换尿布 / 轻拍安抚\n- 【打气小纸条】：一个预留的可爱便签区域，写着“老婆辛苦啦！冰箱里有宵夜！”\nConn的建议：“我和宝妈就靠这个表，分工明确，谁负责谁休息，能减少很多不必要的争吵。记住，先照顾好彼此，才能照顾好娃。”",
      "visual_elements": [
        "美观的表格模板",
        "“打气小纸条”手绘风格设计",
        "夫妻协作小图标",
        "“Conn的建议”模块"
      ],
      "color_scheme": "温馨蓝色系，如#E3F2FD背景搭配蓝色系#1976D2文字",
      "layout": "顶部标题，中间是清晰的表格设计，旁边用对话框形式加入建议",
      "height_constraint": "严格控制在560px以内"
    },
    {
      "image_number": 4,
      "type": "总结图",
      "title": "第三步：温柔调整，告别熊猫眼",
      "main_content": "标题：③ 告别熊猫眼 · 核心总结\n要点列表：\n1. 【先观察，后行动】：别急着抱！给宝宝一个自己尝试接觉的机会。\n2. 【系统化排查】：用清单代替猜测，找到问题的真正源头。\n3. 【夫妻是最佳战队】：明确分工，互相支持，是搞定睡眠难题的最大前提。\n互动引导：\n“希望这份爸爸牌指南能帮到你！点赞收藏，下一个整觉宝宝就是你家！”\n“@你的神队友一起学习！评论区聊聊，你家宝宝夜醒最常见的原因是啥？”",
      "visual_elements": [
        "数字要点列表 '1, 2, 3'",
        "核心金句提炼",
        "醒目的互动引导文案",
        "底部清晰的“@宝爸Conn”署名"
      ],
      "color_scheme": "激励紫色系，如#F3E5F5背景搭配深紫色#6A1B9A元素",
      "layout": "清晰的列表式布局，底部留出足够空间给互动引导和署名",
      "height_constraint": "严格控制在560px以内"
    }
  ],
  "design_principles": {
    "size_constraint": "420x560px（3:4黄金比例）",
    "font_hierarchy": "主标题36px，章节标题22px，正文15px，注释12px",
    "color_palette": [
      "#FFDDBB",
      "#E8F5E9",
      "#E3F2FD",
      "#F3E5F5"
    ],
    "spacing": "页面内边距上下25px、左右20px，主要元素间距15px，确保呼吸感",
    "visual_consistency": "统一使用圆角矩形作为信息卡片，字体、图标风格保持一致，每张图右下角都有'@宝爸Conn'水印"
  }
}